autorec/__init__.py
autorec-0.0.1.dist-info/LICENSE.txt
autorec-0.0.1.dist-info/METADATA
autorec-0.0.1.dist-info/WHEEL
autorec-0.0.1.dist-info/top_level.txt
autorec-0.0.1.dist-info/RECORD
